image_to_arduino/__init__.py
image_to_arduino/__main__.py
image_to_arduino/main.py
image_to_arduino/icon/icon.png
image_to_arduino-1.0.4.6.data/data/image_to_arduino/icon/icon.png
image_to_arduino-1.0.4.6.dist-info/LICENSE
image_to_arduino-1.0.4.6.dist-info/METADATA
image_to_arduino-1.0.4.6.dist-info/WHEEL
image_to_arduino-1.0.4.6.dist-info/entry_points.txt
image_to_arduino-1.0.4.6.dist-info/top_level.txt
image_to_arduino-1.0.4.6.dist-info/RECORD
